{
    "decks": [
      {
        "name": "Major Arcana",
        "cards": [0, 1, 2, 3, 4, 5, 6, 7, 8, 9, 10, 11, 12, 13, 14, 15, 16, 17, 18, 19, 20, 21]
      }
    ],
    "layouts": [
      {
        "name": "Card of the Day",
        "cardAmount": 1,
        "cardPositions": [
          {
            "position": 0,
            "name": "Card of the Day"
          }
        ]
      },
      {
        "name": "Spiritual Guidance",
        "cardAmount": 8,
        "cardPositions": [
          {
            "position": 1,
            "name": "Primary Focus"
          },
          {
            "position": 2,
            "name": "Your Motivation"
          },
          {
            "position": 3,
            "name": "Anxieties"
          },
          {
            "position": 4,
            "name": "Hidden Influences"
          },
          {
            "position": 5,
            "name": "Advice"
          },
          {
            "position": 6,
            "name": "Best Path Forward"
          },
          {
            "position": 7,
            "name": "Keep In Mind"
          },
          {
            "position": 8,
            "name": "Ideal Outcome"
          }
        ]
      }
    ],
    "cards": [
      
      
        {
          "name": "The Fool",
          "id": 0,
          "image": "/assets/card_images/the-fool.jpg",
          "descriptions": [
            {"layoutName": "Card of the Day", "position": 1, "descriptionUpright": "", "descriptionReversed": ""},
            {"layoutName": "Spiritual Guidance", "position": 1, "descriptionUpright": "Description for The Fool Upright in Position 1", "descriptionReversed": "Description for The Fool Reversed in Position 1"},
            {"layoutName": "Spiritual Guidance", "position": 2, "descriptionUpright": "Description for The Fool Upright in Position 2", "descriptionReversed": "Description for The Fool Reversed in Position 2"},
            {"layoutName": "Spiritual Guidance", "position": 3, "descriptionUpright": "Description for The Fool Upright in Position 3", "descriptionReversed": "Description for The Fool Reversed in Position 3"},
            {"layoutName": "Spiritual Guidance", "position": 4, "descriptionUpright": "Description for The Fool Upright in Position 4", "descriptionReversed": "Description for The Fool Reversed in Position 4"},
            {"layoutName": "Spiritual Guidance", "position": 5, "descriptionUpright": "Description for The Fool Upright in Position 5", "descriptionReversed": "Description for The Fool Reversed in Position 5"},
            {"layoutName": "Spiritual Guidance", "position": 6, "descriptionUpright": "Description for The Fool Upright in Position 6", "descriptionReversed": "Description for The Fool Reversed in Position 6"},
            {"layoutName": "Spiritual Guidance", "position": 7, "descriptionUpright": "Description for The Fool Upright in Position 7", "descriptionReversed": "Description for The Fool Reversed in Position 7"},
            {"layoutName": "Spiritual Guidance", "position": 8, "descriptionUpright": "Description for The Fool Upright in Position 8", "descriptionReversed": "Description for The Fool Reversed in Position 8"}
          ]
        },
        {
          "name": "The Magician",
          "id": 1,
          "image": "/assets/card_images/the-magician.jpg",
          "descriptions": [
            {"layoutName": "Card of the Day", "position": 1, "descriptionUpright": "", "descriptionReversed": ""},
            {"layoutName": "Spiritual Guidance", "position": 1, "descriptionUpright": "Description for The Magician Upright in Position 1", "descriptionReversed": "Description for The Magician Reversed in Position 1"},
            {"layoutName": "Spiritual Guidance", "position": 2, "descriptionUpright": "Description for The Magician Upright in Position 2", "descriptionReversed": "Description for The Magician Reversed in Position 2"},
            {"layoutName": "Spiritual Guidance", "position": 3, "descriptionUpright": "Description for The Magician Upright in Position 3", "descriptionReversed": "Description for The Magician Reversed in Position 3"},
            {"layoutName": "Spiritual Guidance", "position": 4, "descriptionUpright": "Description for The Magician Upright in Position 4", "descriptionReversed": "Description for The Magician Reversed in Position 4"},
            {"layoutName": "Spiritual Guidance", "position": 5, "descriptionUpright": "Description for The Magician Upright in Position 5", "descriptionReversed": "Description for The Magician Reversed in Position 5"},
            {"layoutName": "Spiritual Guidance", "position": 6, "descriptionUpright": "Description for The Magician Upright in Position 6", "descriptionReversed": "Description for The Magician Reversed in Position 6"},
            {"layoutName": "Spiritual Guidance", "position": 7, "descriptionUpright": "Description for The Magician Upright in Position 7", "descriptionReversed": "Description for The Magician Reversed in Position 7"},
            {"layoutName": "Spiritual Guidance", "position": 8, "descriptionUpright": "Description for The Magician Upright in Position 8", "descriptionReversed": "Description for The Magician Reversed in Position 8"}
          ]
        },
        {
          "name": "The High Priestess",
          "id": 2,
          "image": "/assets/card_images/the-high-priestess.jpg",
          "descriptions": [
            {"layoutName": "Card of the Day", "position": 1, "descriptionUpright": "", "descriptionReversed": ""},
            {"layoutName": "Spiritual Guidance", "position": 1, "descriptionUpright": "Description for The High Priestess Upright in Position 1", "descriptionReversed": "Description for The High Priestess Reversed in Position 1"},
            {"layoutName": "Spiritual Guidance", "position": 2, "descriptionUpright": "Description for The High Priestess Upright in Position 2", "descriptionReversed": "Description for The High Priestess Reversed in Position 2"},
            {"layoutName": "Spiritual Guidance", "position": 3, "descriptionUpright": "Description for The High Priestess Upright in Position 3", "descriptionReversed": "Description for The High Priestess Reversed in Position 3"},
            {"layoutName": "Spiritual Guidance", "position": 4, "descriptionUpright": "Description for The High Priestess Upright in Position 4", "descriptionReversed": "Description for The High Priestess Reversed in Position 4"},
            {"layoutName": "Spiritual Guidance", "position": 5, "descriptionUpright": "Description for The High Priestess Upright in Position 5", "descriptionReversed": "Description for The High Priestess Reversed in Position 5"},
            {"layoutName": "Spiritual Guidance", "position": 6, "descriptionUpright": "Description for The High Priestess Upright in Position 6", "descriptionReversed": "Description for The High Priestess Reversed in Position 6"},
            {"layoutName": "Spiritual Guidance", "position": 7, "descriptionUpright": "Description for The High Priestess Upright in Position 7", "descriptionReversed": "Description for The High Priestess Reversed in Position 7"},
            {"layoutName": "Spiritual Guidance", "position": 8, "descriptionUpright": "Description for The High Priestess Upright in Position 8", "descriptionReversed": "Description for The High Priestess Reversed in Position 8"}
          ]
        },
        {
          "name": "The Empress",
          "id": 3,
          "image": "/assets/card_images/the-empress.jpg",
          "descriptions": [
            {"layoutName": "Card of the Day", "position": 1, "descriptionUpright": "", "descriptionReversed": ""},
            {"layoutName": "Spiritual Guidance", "position": 1, "descriptionUpright": "Description for The Empress Upright in Position 1", "descriptionReversed": "Description for The Empress Reversed in Position 1"},
            {"layoutName": "Spiritual Guidance", "position": 2, "descriptionUpright": "Description for The Empress Upright in Position 2", "descriptionReversed": "Description for The Empress Reversed in Position 2"},
            {"layoutName": "Spiritual Guidance", "position": 3, "descriptionUpright": "Description for The Empress Upright in Position 3", "descriptionReversed": "Description for The Empress Reversed in Position 3"},
            {"layoutName": "Spiritual Guidance", "position": 4, "descriptionUpright": "Description for The Empress Upright in Position 4", "descriptionReversed": "Description for The Empress Reversed in Position 4"},
            {"layoutName": "Spiritual Guidance", "position": 5, "descriptionUpright": "Description for The Empress Upright in Position 5", "descriptionReversed": "Description for The Empress Reversed in Position 5"},
            {"layoutName": "Spiritual Guidance", "position": 6, "descriptionUpright": "Description for The Empress Upright in Position 6", "descriptionReversed": "Description for The Empress Reversed in Position 6"},
            {"layoutName": "Spiritual Guidance", "position": 7, "descriptionUpright": "Description for The Empress Upright in Position 7", "descriptionReversed": "Description for The Empress Reversed in Position 7"},
            {"layoutName": "Spiritual Guidance", "position": 8, "descriptionUpright": "Description for The Empress Upright in Position 8", "descriptionReversed": "Description for The Empress Reversed in Position 8"}
          ]
        },
        {
          "name": "The Emperor",
          "id": 4,
          "image": "/assets/card_images/the-emperor.jpg",
          "descriptions": [
            {"layoutName": "Card of the Day", "position": 1, "descriptionUpright": "", "descriptionReversed": ""},
            {"layoutName": "Spiritual Guidance", "position": 1, "descriptionUpright": "Description for The Emperor Upright in Position 1", "descriptionReversed": "Description for The Emperor Reversed in Position 1"},
            {"layoutName": "Spiritual Guidance", "position": 2, "descriptionUpright": "Description for The Emperor Upright in Position 2", "descriptionReversed": "Description for The Emperor Reversed in Position 2"},
            {"layoutName": "Spiritual Guidance", "position": 3, "descriptionUpright": "Description for The Emperor Upright in Position 3", "descriptionReversed": "Description for The Emperor Reversed in Position 3"},
            {"layoutName": "Spiritual Guidance", "position": 4, "descriptionUpright": "Description for The Emperor Upright in Position 4", "descriptionReversed": "Description for The Emperor Reversed in Position 4"},
            {"layoutName": "Spiritual Guidance", "position": 5, "descriptionUpright": "Description for The Emperor Upright in Position 5", "descriptionReversed": "Description for The Emperor Reversed in Position 5"},
            {"layoutName": "Spiritual Guidance", "position": 6, "descriptionUpright": "Description for The Emperor Upright in Position 6", "descriptionReversed": "Description for The Emperor Reversed in Position 6"},
            {"layoutName": "Spiritual Guidance", "position": 7, "descriptionUpright": "Description for The Emperor Upright in Position 7", "descriptionReversed": "Description for The Emperor Reversed in Position 7"},
            {"layoutName": "Spiritual Guidance", "position": 8, "descriptionUpright": "Description for The Emperor Upright in Position 8", "descriptionReversed": "Description for The Emperor Reversed in Position 8"}
          ]
        },
        {
          "name": "The Hierophant",
          "id": 5,
          "image": "/assets/card_images/the-hierophant.jpg",
          "descriptions": [
            {"layoutName": "Card of the Day", "position": 1, "descriptionUpright": "", "descriptionReversed": ""},
            {"layoutName": "Spiritual Guidance", "position": 1, "descriptionUpright": "Description for The Hierophant Upright in Position 1", "descriptionReversed": "Description for The Hierophant Reversed in Position 1"},
            {"layoutName": "Spiritual Guidance", "position": 2, "descriptionUpright": "Description for The Hierophant Upright in Position 2", "descriptionReversed": "Description for The Hierophant Reversed in Position 2"},
            {"layoutName": "Spiritual Guidance", "position": 3, "descriptionUpright": "Description for The Hierophant Upright in Position 3", "descriptionReversed": "Description for The Hierophant Reversed in Position 3"},
            {"layoutName": "Spiritual Guidance", "position": 4, "descriptionUpright": "Description for The Hierophant Upright in Position 4", "descriptionReversed": "Description for The Hierophant Reversed in Position 4"},
            {"layoutName": "Spiritual Guidance", "position": 5, "descriptionUpright": "Description for The Hierophant Upright in Position 5", "descriptionReversed": "Description for The Hierophant Reversed in Position 5"},
            {"layoutName": "Spiritual Guidance", "position": 6, "descriptionUpright": "Description for The Hierophant Upright in Position 6", "descriptionReversed": "Description for The Hierophant Reversed in Position 6"},
            {"layoutName": "Spiritual Guidance", "position": 7, "descriptionUpright": "Description for The Hierophant Upright in Position 7", "descriptionReversed": "Description for The Hierophant Reversed in Position 7"},
            {"layoutName": "Spiritual Guidance", "position": 8, "descriptionUpright": "Description for The Hierophant Upright in Position 8", "descriptionReversed": "Description for The Hierophant Reversed in Position 8"}
          ]
        },
        {
          "name": "The Lovers",
          "id": 6,
          "image": "/assets/card_images/the-lovers.jpg",
          "descriptions": [
            {"layoutName": "Card of the Day", "position": 1, "descriptionUpright": "", "descriptionReversed": ""},
            {"layoutName": "Spiritual Guidance", "position": 1, "descriptionUpright": "Description for The Lovers Upright in Position 1", "descriptionReversed": "Description for The Lovers Reversed in Position 1"},
            {"layoutName": "Spiritual Guidance", "position": 2, "descriptionUpright": "Description for The Lovers Upright in Position 2", "descriptionReversed": "Description for The Lovers Reversed in Position 2"},
            {"layoutName": "Spiritual Guidance", "position": 3, "descriptionUpright": "Description for The Lovers Upright in Position 3", "descriptionReversed": "Description for The Lovers Reversed in Position 3"},
            {"layoutName": "Spiritual Guidance", "position": 4, "descriptionUpright": "Description for The Lovers Upright in Position 4", "descriptionReversed": "Description for The Lovers Reversed in Position 4"},
            {"layoutName": "Spiritual Guidance", "position": 5, "descriptionUpright": "Description for The Lovers Upright in Position 5", "descriptionReversed": "Description for The Lovers Reversed in Position 5"},
            {"layoutName": "Spiritual Guidance", "position": 6, "descriptionUpright": "Description for The Lovers Upright in Position 6", "descriptionReversed": "Description for The Lovers Reversed in Position 6"},
            {"layoutName": "Spiritual Guidance", "position": 7, "descriptionUpright": "Description for The Lovers Upright in Position 7", "descriptionReversed": "Description for The Lovers Reversed in Position 7"},
            {"layoutName": "Spiritual Guidance", "position": 8, "descriptionUpright": "Description for The Lovers Upright in Position 8", "descriptionReversed": "Description for The Lovers Reversed in Position 8"}
          ]
        },
        {
          "name": "The Chariot",
          "id": 7,
          "image": "/assets/card_images/the-chariot.jpg",
          "descriptions": [
            {"layoutName": "Card of the Day", "position": 1, "descriptionUpright": "", "descriptionReversed": ""},
            {"layoutName": "Spiritual Guidance", "position": 1, "descriptionUpright": "Description for The Chariot Upright in Position 1", "descriptionReversed": "Description for The Chariot Reversed in Position 1"},
            {"layoutName": "Spiritual Guidance", "position": 2, "descriptionUpright": "Description for The Chariot Upright in Position 2", "descriptionReversed": "Description for The Chariot Reversed in Position 2"},
            {"layoutName": "Spiritual Guidance", "position": 3, "descriptionUpright": "Description for The Chariot Upright in Position 3", "descriptionReversed": "Description for The Chariot Reversed in Position 3"},
            {"layoutName": "Spiritual Guidance", "position": 4, "descriptionUpright": "Description for The Chariot Upright in Position 4", "descriptionReversed": "Description for The Chariot Reversed in Position 4"},
            {"layoutName": "Spiritual Guidance", "position": 5, "descriptionUpright": "Description for The Chariot Upright in Position 5", "descriptionReversed": "Description for The Chariot Reversed in Position 5"},
            {"layoutName": "Spiritual Guidance", "position": 6, "descriptionUpright": "Description for The Chariot Upright in Position 6", "descriptionReversed": "Description for The Chariot Reversed in Position 6"},
            {"layoutName": "Spiritual Guidance", "position": 7, "descriptionUpright": "Description for The Chariot Upright in Position 7", "descriptionReversed": "Description for The Chariot Reversed in Position 7"},
            {"layoutName": "Spiritual Guidance", "position": 8, "descriptionUpright": "Description for The Chariot Upright in Position 8", "descriptionReversed": "Description for The Chariot Reversed in Position 8"}
          ]
        },
        {
          "name": "Strength",
          "id": 8,
          "image": "/assets/card_images/strength.jpg",
          "descriptions": [
            {"layoutName": "Spiritual Guidance", "position": 1, "descriptionUpright": "Description for Strength Upright in Position 1", "descriptionReversed": "Description for Strength Reversed in Position 1"},
            {"layoutName": "Spiritual Guidance", "position": 2, "descriptionUpright": "Description for Strength Upright in Position 2", "descriptionReversed": "Description for Strength Reversed in Position 2"},
            {"layoutName": "Spiritual Guidance", "position": 3, "descriptionUpright": "Description for Strength Upright in Position 3", "descriptionReversed": "Description for Strength Reversed in Position 3"},
            {"layoutName": "Spiritual Guidance", "position": 4, "descriptionUpright": "Description for Strength Upright in Position 4", "descriptionReversed": "Description for Strength Reversed in Position 4"},
            {"layoutName": "Spiritual Guidance", "position": 5, "descriptionUpright": "Description for Strength Upright in Position 5", "descriptionReversed": "Description for Strength Reversed in Position 5"},
            {"layoutName": "Spiritual Guidance", "position": 6, "descriptionUpright": "Description for Strength Upright in Position 6", "descriptionReversed": "Description for Strength Reversed in Position 6"},
            {"layoutName": "Spiritual Guidance", "position": 7, "descriptionUpright": "Description for Strength Upright in Position 7", "descriptionReversed": "Description for Strength Reversed in Position 7"},
            {"layoutName": "Spiritual Guidance", "position": 8, "descriptionUpright": "Description for Strength Upright in Position 8", "descriptionReversed": "Description for Strength Reversed in Position 8"}
          ]
        },
        {
          "name": "The Hermit",
          "id": 9,
          "image": "/assets/card_images/the-hermit.jpg",
          "descriptions": [
            {"layoutName": "Spiritual Guidance", "position": 1, "descriptionUpright": "Description for The Hermit Upright in Position 1", "descriptionReversed": "Description for The Hermit Reversed in Position 1"},
            {"layoutName": "Spiritual Guidance", "position": 2, "descriptionUpright": "Description for The Hermit Upright in Position 2", "descriptionReversed": "Description for The Hermit Reversed in Position 2"},
            {"layoutName": "Spiritual Guidance", "position": 3, "descriptionUpright": "Description for The Hermit Upright in Position 3", "descriptionReversed": "Description for The Hermit Reversed in Position 3"},
            {"layoutName": "Spiritual Guidance", "position": 4, "descriptionUpright": "Description for The Hermit Upright in Position 4", "descriptionReversed": "Description for The Hermit Reversed in Position 4"},
            {"layoutName": "Spiritual Guidance", "position": 5, "descriptionUpright": "Description for The Hermit Upright in Position 5", "descriptionReversed": "Description for The Hermit Reversed in Position 5"},
            {"layoutName": "Spiritual Guidance", "position": 6, "descriptionUpright": "Description for The Hermit Upright in Position 6", "descriptionReversed": "Description for The Hermit Reversed in Position 6"},
            {"layoutName": "Spiritual Guidance", "position": 7, "descriptionUpright": "Description for The Hermit Upright in Position 7", "descriptionReversed": "Description for The Hermit Reversed in Position 7"},
            {"layoutName": "Spiritual Guidance", "position": 8, "descriptionUpright": "Description for The Hermit Upright in Position 8", "descriptionReversed": "Description for The Hermit Reversed in Position 8"}
          ]
        },
        {
          "name": "Wheel of Fortune",
          "id": 10,
          "image": "/assets/card_images/wheel-of-fortune.jpg",
          "descriptions": [
            {"layoutName": "Spiritual Guidance", "position": 1, "descriptionUpright": "Description for Wheel of Fortune Upright in Position 1", "descriptionReversed": "Description for Wheel of Fortune Reversed in Position 1"},
            {"layoutName": "Spiritual Guidance", "position": 2, "descriptionUpright": "Description for Wheel of Fortune Upright in Position 2", "descriptionReversed": "Description for Wheel of Fortune Reversed in Position 2"},
            {"layoutName": "Spiritual Guidance", "position": 3, "descriptionUpright": "Description for Wheel of Fortune Upright in Position 3", "descriptionReversed": "Description for Wheel of Fortune Reversed in Position 3"},
            {"layoutName": "Spiritual Guidance", "position": 4, "descriptionUpright": "Description for Wheel of Fortune Upright in Position 4", "descriptionReversed": "Description for Wheel of Fortune Reversed in Position 4"},
            {"layoutName": "Spiritual Guidance", "position": 5, "descriptionUpright": "Description for Wheel of Fortune Upright in Position 5", "descriptionReversed": "Description for Wheel of Fortune Reversed in Position 5"},
            {"layoutName": "Spiritual Guidance", "position": 6, "descriptionUpright": "Description for Wheel of Fortune Upright in Position 6", "descriptionReversed": "Description for Wheel of Fortune Reversed in Position 6"},
            {"layoutName": "Spiritual Guidance", "position": 7, "descriptionUpright": "Description for Wheel of Fortune Upright in Position 7", "descriptionReversed": "Description for Wheel of Fortune Reversed in Position 7"},
            {"layoutName": "Spiritual Guidance", "position": 8, "descriptionUpright": "Description for Wheel of Fortune Upright in Position 8", "descriptionReversed": "Description for Wheel of Fortune Reversed in Position 8"}
          ]
        },
        {
          "name": "Justice",
          "id": 11,
          "image": "/assets/card_images/justice.jpg",
          "descriptions": [
            {"layoutName": "Spiritual Guidance", "position": 1, "descriptionUpright": "Description for Justice Upright in Position 1", "descriptionReversed": "Description for Justice Reversed in Position 1"},
            {"layoutName": "Spiritual Guidance", "position": 2, "descriptionUpright": "Description for Justice Upright in Position 2", "descriptionReversed": "Description for Justice Reversed in Position 2"},
            {"layoutName": "Spiritual Guidance", "position": 3, "descriptionUpright": "Description for Justice Upright in Position 3", "descriptionReversed": "Description for Justice Reversed in Position 3"},
            {"layoutName": "Spiritual Guidance", "position": 4, "descriptionUpright": "Description for Justice Upright in Position 4", "descriptionReversed": "Description for Justice Reversed in Position 4"},
            {"layoutName": "Spiritual Guidance", "position": 5, "descriptionUpright": "Description for Justice Upright in Position 5", "descriptionReversed": "Description for Justice Reversed in Position 5"},
            {"layoutName": "Spiritual Guidance", "position": 6, "descriptionUpright": "Description for Justice Upright in Position 6", "descriptionReversed": "Description for Justice Reversed in Position 6"},
            {"layoutName": "Spiritual Guidance", "position": 7, "descriptionUpright": "Description for Justice Upright in Position 7", "descriptionReversed": "Description for Justice Reversed in Position 7"},
            {"layoutName": "Spiritual Guidance", "position": 8, "descriptionUpright": "Description for Justice Upright in Position 8", "descriptionReversed": "Description for Justice Reversed in Position 8"}
          ]
        }
      
      
      
    ]
  }
  